stos/__init__.py
stos/sign_to_speech/__init__.py
stos/sign_to_speech/model.py
stos/sign_to_speech/model_prepare.py
stos/sign_to_speech/parser.py
stos/sign_to_speech/sign_to_speech.py
stos/sign_to_speech/speak.py
stos/speech_to_sign/__init__.py
stos/speech_to_sign/animate.py
stos/speech_to_sign/audio_recording.py
stos/speech_to_sign/speech_to_sign.py
stos/speech_to_sign/speech_to_text.py
stos-1.0.2.dist-info/LICENCE
stos-1.0.2.dist-info/METADATA
stos-1.0.2.dist-info/WHEEL
stos-1.0.2.dist-info/top_level.txt
stos-1.0.2.dist-info/RECORD
