Metadata-Version: 2.1
Name: stos
Version: 1.0.2
Summary: Converting the American sign language into speech or text, and vice versa.
Home-page: https://github.com/azizmousa/sign_language_translator
Author: azizmousa
Author-email: azizmousa1010@gmail.com
License: MIT
Keywords: ASL translation
Platform: UNKNOWN
Classifier: Intended Audience :: Education
Classifier: Operating System :: OS Independent
Classifier: License :: OSI Approved :: MIT License
Classifier: Programming Language :: Python :: 3.8
Requires-Dist: Keras-Preprocessing (==1.1.2)
Requires-Dist: Markdown (==3.3.6)
Requires-Dist: Pillow (==8.4.0)
Requires-Dist: PyYAML (==6.0)
Requires-Dist: SpeechRecognition (==3.8.1)
Requires-Dist: Werkzeug (==2.0.2)
Requires-Dist: absl-py (==1.0.0)
Requires-Dist: aiohttp (==3.8.1)
Requires-Dist: aiosignal (==1.2.0)
Requires-Dist: astunparse (==1.6.3)
Requires-Dist: async-timeout (==4.0.2)
Requires-Dist: attrs (==21.2.0)
Requires-Dist: cachetools (==4.2.4)
Requires-Dist: certifi (==2021.10.8)
Requires-Dist: cffi (==1.15.0)
Requires-Dist: charset-normalizer (==2.0.9)
Requires-Dist: click (==8.0.3)
Requires-Dist: cycler (==0.11.0)
Requires-Dist: datasets (==1.17.0)
Requires-Dist: dill (==0.3.4)
Requires-Dist: filelock (==3.4.1)
Requires-Dist: flatbuffers (==2.0)
Requires-Dist: fonttools (==4.28.1)
Requires-Dist: frozenlist (==1.2.0)
Requires-Dist: fsspec (==2021.11.1)
Requires-Dist: gTTS (==2.2.3)
Requires-Dist: gast (==0.4.0)
Requires-Dist: google-auth-oauthlib (==0.4.6)
Requires-Dist: google-auth (==2.3.3)
Requires-Dist: google-pasta (==0.2.0)
Requires-Dist: grpcio (==1.43.0)
Requires-Dist: h5py (==3.6.0)
Requires-Dist: happytransformer (==2.4.0)
Requires-Dist: huggingface-hub (==0.2.1)
Requires-Dist: idna (==3.3)
Requires-Dist: importlib-metadata (==4.10.0)
Requires-Dist: joblib (==1.1.0)
Requires-Dist: keras (==2.7.0)
Requires-Dist: kiwisolver (==1.3.2)
Requires-Dist: libclang (==12.0.0)
Requires-Dist: matplotlib (==3.5.0)
Requires-Dist: mediapipe (==0.8.9)
Requires-Dist: multidict (==5.2.0)
Requires-Dist: multiprocess (==0.70.12.2)
Requires-Dist: nltk (==3.6.6)
Requires-Dist: numpy (==1.21.4)
Requires-Dist: oauthlib (==3.1.1)
Requires-Dist: opencv-contrib-python (==4.5.4.58)
Requires-Dist: opencv-python (==4.5.4.58)
Requires-Dist: opt-einsum (==3.3.0)
Requires-Dist: packaging (==21.3)
Requires-Dist: pandas (==1.3.4)
Requires-Dist: playsound (==1.3.0)
Requires-Dist: protobuf (==3.19.1)
Requires-Dist: pyarrow (==6.0.1)
Requires-Dist: pyasn1-modules (==0.2.8)
Requires-Dist: pyasn1 (==0.4.8)
Requires-Dist: pycparser (==2.21)
Requires-Dist: pyparsing (==3.0.6)
Requires-Dist: python-dateutil (==2.8.2)
Requires-Dist: pytz (==2021.3)
Requires-Dist: regex (==2021.11.10)
Requires-Dist: requests-oauthlib (==1.3.0)
Requires-Dist: requests (==2.26.0)
Requires-Dist: rsa (==4.8)
Requires-Dist: sacremoses (==0.0.46)
Requires-Dist: sentencepiece (==0.1.96)
Requires-Dist: setuptools-scm (==6.3.2)
Requires-Dist: simplejson (==3.17.6)
Requires-Dist: six (==1.16.0)
Requires-Dist: sounddevice (==0.4.3)
Requires-Dist: tensorboard-data-server (==0.6.1)
Requires-Dist: tensorboard-plugin-wit (==1.8.0)
Requires-Dist: tensorboard (==2.7.0)
Requires-Dist: tensorflow-estimator (==2.7.0)
Requires-Dist: tensorflow-io-gcs-filesystem (==0.23.1)
Requires-Dist: tensorflow (==2.7.0)
Requires-Dist: termcolor (==1.1.0)
Requires-Dist: tokenizers (==0.10.3)
Requires-Dist: tomli (==1.2.2)
Requires-Dist: torch (==1.10.1)
Requires-Dist: tqdm (==4.62.3)
Requires-Dist: transformers (==4.15.0)
Requires-Dist: typing-extensions (==4.0.1)
Requires-Dist: urllib3 (==1.26.7)
Requires-Dist: wavio (==0.0.4)
Requires-Dist: wrapt (==1.13.3)
Requires-Dist: xxhash (==2.0.2)
Requires-Dist: yarl (==1.7.2)
Requires-Dist: zipp (==3.6.0)
